zsft.recipe.cmd-0.4-py2.7-nspkg.pth
zsft/recipe/cmd/shell.py
zsft.recipe.cmd-0.4.dist-info/DESCRIPTION.rst
zsft.recipe.cmd-0.4.dist-info/METADATA
zsft.recipe.cmd-0.4.dist-info/RECORD
zsft.recipe.cmd-0.4.dist-info/WHEEL
zsft.recipe.cmd-0.4.dist-info/entry_points.txt
zsft.recipe.cmd-0.4.dist-info/metadata.json
zsft.recipe.cmd-0.4.dist-info/namespace_packages.txt
zsft.recipe.cmd-0.4.dist-info/top_level.txt
zsft.recipe.cmd-0.4.dist-info/zip-safe
