Metadata-Version: 2.0
Name: zsft.recipe.cmd
Version: 0.4
Summary: Buildout recipe to execute commands via shell or python
Home-page: https://github.com/zartsoft/zsft.recipe.cmd/
Author: Zart Software
Author-email: project-zsft.recipe.cmd@zartsoft.ru
License: MIT
Keywords: buildout recipe shell
Platform: UNKNOWN
Classifier: Development Status :: 4 - Beta
Classifier: Intended Audience :: Developers
Classifier: License :: OSI Approved :: MIT License
Classifier: Programming Language :: Python
Classifier: Programming Language :: Python :: 2
Classifier: Programming Language :: Python :: 2.7
Classifier: Programming Language :: Python :: 3
Classifier: Programming Language :: Python :: 3.4
Classifier: Programming Language :: Python :: 3.5
Classifier: Programming Language :: Python :: 3.6
Classifier: Operating System :: OS Independent
Classifier: Framework :: Buildout
Classifier: Framework :: Buildout :: Recipe
Requires-Dist: setuptools
Requires-Dist: zc.buildout
